smolstore/__init__.py
smolstore/document.py
smolstore/exceptions.py
smolstore/field.py
smolstore/fields.py
smolstore/query.py
smolstore/serializers.py
smolstore/store.py
smolstore/table.py
smolstore-0.2.1a0.dist-info/LICENSE
smolstore-0.2.1a0.dist-info/WHEEL
smolstore-0.2.1a0.dist-info/METADATA
smolstore-0.2.1a0.dist-info/RECORD
