Metadata-Version: 2.1
Name: smolstore
Version: 0.2.1a0
Summary: A simple in-memory Python document store
Home-page: https://github.com/raybotha/smolstore
License: LGPL-3.0+
Author: Raymond Botha
Author-email: botha@riseup.net
Requires-Python: >=3.6,<4.0
Classifier: License :: OSI Approved :: GNU Lesser General Public License v3 or later (LGPLv3+)
Classifier: Programming Language :: Python :: 3
Classifier: Programming Language :: Python :: 3.6
Classifier: Programming Language :: Python :: 3.7
Classifier: Topic :: Database
Classifier: Topic :: Software Development :: Libraries :: Python Modules
Project-URL: Repository, https://github.com/raybotha/smolstore
